{
  "name": "Elizabeth Haynes",
  "age": 31,
  "address": {
    "street": "Mera Mill",
    "city": "Segtice",
    "state": "KS",
    "zip": "33531"
  },
  "contact": {
    "phone": "(749) 650-1874",
    "servicePhone": "800867276"
  },
  "birthday": "1974-09-11T14:27:43.344Z",
  "ip": "249.177.177.251",
  "foo": "bar",
  "profile": {
    "about": "Ozwulkit zu perruv husaiju duhpiije zaszeg sel ajuzut dun kiwam kezvik siino wu ci ahe ika abosipjah. Zaj se lagvedi gumvu fabkunnur lekezsit jujsolo umiza cuwomru ejimoda wohbenpel suvdo. Soseka cirwo binimtez germig bew hethir ru vemisa nioju cejompa irozuj johion kuj nasmiv.",
    "bio": "Geg icuedo jizfeziv civetzi fovitilu zultisnut pucov kep pujreb bisohec nahi vi. Vapahiape vikifma mujsubcu bo afurila jipmelwoc pemigiwu hed vu livof wotepen otohapiw zartego. Jupu buv laasiwe hokihze gucih fapdaw kebip zeuwi fo zuvuncuw go lu rob gakpe samagfih. Wid olapu rekcu piv zem bojwi ke puczuane buderes hudu oseor vuvgub tidevat bed. Bevu tociked dason dilalcej eh zammibef rimohzim zabamkuh pokim nu cobu ema or."
  },
  "apiKey": "f411301344b9e3f2016a13b01a90fbec3b3431805ddeda76f8daf3639074861d",
  "currency": {
    "code": "GHS",
    "name": "Ghana Cedi"
  }
}